MANIFEST.in
account_chart_template.xml
account_chart_template.yml
account_demo.xml
account_financial_report.xml
account_fiscal_position_tax_template.xml
account_pcmn_belgium.xml
account_tax_code_template.xml
account_tax_template.xml
fiscal_templates.xml
l10n_be_sequence.xml
pcmn.csv
pcmn3.csv
setup.py
./__init__.py
./__openerp__.py
./wizard/__init__.py
./wizard/l10n_be_account_vat_declaration.py
./wizard/l10n_be_partner_vat_listing.py
./wizard/l10n_be_vat_intra.py
i18n/ar.po
i18n/bg.po
i18n/bs.po
i18n/ca.po
i18n/cs.po
i18n/da.po
i18n/de.po
i18n/en_GB.po
i18n/es.po
i18n/es_AR.po
i18n/es_CR.po
i18n/es_MX.po
i18n/es_VE.po
i18n/et.po
i18n/fi.po
i18n/fr.po
i18n/gl.po
i18n/hr.po
i18n/hu.po
i18n/id.po
i18n/it.po
i18n/ja.po
i18n/ko.po
i18n/ko_KO.po
i18n/l10n_be.pot
i18n/lt.po
i18n/mk.po
i18n/nl.po
i18n/nl_BE.po
i18n/pl.po
i18n/pt.po
i18n/pt_BR.po
i18n/ro.po
i18n/ru.po
i18n/sl.po
i18n/sq.po
i18n/sr@latin.po
i18n/sv.po
i18n/tlh.po
i18n/tr.po
i18n/uk.po
i18n/vi.po
i18n/zh_CN.po
i18n/zh_TW.po
i18n/znd_ZND.po
i18n_extra/nl_BE.po
images/1_config_chart_l10n_be.jpeg
images/2_l10n_be_chart.jpeg
openerp_l10n_be.egg-info/PKG-INFO
openerp_l10n_be.egg-info/SOURCES.txt
openerp_l10n_be.egg-info/dependency_links.txt
openerp_l10n_be.egg-info/requires.txt
openerp_l10n_be.egg-info/top_level.txt
security/ir.model.access.csv
static/src/img/icon.png
wizard/account_wizard.xml
wizard/l10n_be_account_vat_declaration_view.xml
wizard/l10n_be_partner_vat_listing.rml
wizard/l10n_be_partner_vat_listing.xml
wizard/l10n_be_vat_intra_print.rml
wizard/l10n_be_vat_intra_view.xml